pyerge/__init__.py
pyerge/cli.py
pyerge/glsa.py
pyerge/tmerge.py
pyerge/tools.py
pyerge/utils.py
pyerge-0.7.2.dist-info/LICENSE.md
pyerge-0.7.2.dist-info/METADATA
pyerge-0.7.2.dist-info/WHEEL
pyerge-0.7.2.dist-info/entry_points.txt
pyerge-0.7.2.dist-info/top_level.txt
pyerge-0.7.2.dist-info/RECORD
