Metadata-Version: 2.1
Name: pyerge
Version: 0.7.2
Summary: It is Python wrapper tool for emerge (Gentoo package manager - Portage). It can mount RAM disk of defined size and compile packages inside it
Home-page: https://github.com/emcek/pyerge
Author: Michal Plichta
License: MIT License
Project-URL: Bug Reports, https://github.com/emcek/pyerge/issues
Project-URL: Source, https://github.com/emcek/pyerge
Keywords: gentoo portage emerge conky linux
Classifier: Development Status :: 5 - Production/Stable
Classifier: Environment :: Console
Classifier: Environment :: X11 Applications
Classifier: License :: OSI Approved :: MIT License
Classifier: Operating System :: POSIX
Classifier: Operating System :: Unix
Classifier: Programming Language :: Python :: 3
Classifier: Programming Language :: Python :: 3.6
Classifier: Programming Language :: Python :: 3.7
Classifier: Programming Language :: Python :: 3.8
Classifier: Programming Language :: Python :: 3.9
Classifier: Programming Language :: Python :: 3.10
Classifier: Topic :: Desktop Environment
Classifier: Topic :: Software Development
Classifier: Topic :: Software Development :: Libraries :: Python Modules
Classifier: Topic :: System :: Monitoring
Classifier: Topic :: Utilities
Requires-Python: >=3.6
License-File: LICENSE.md
Requires-Dist: beautifulsoup4
Provides-Extra: testing
Requires-Dist: pytest ; extra == 'testing'
